IQA/__init__.py
IQA/iqa_calculator.py
iqa_calculator-2.0.0.dist-info/licenses/LICENSE
iqa_calculator-2.0.0.dist-info/METADATA
iqa_calculator-2.0.0.dist-info/WHEEL
iqa_calculator-2.0.0.dist-info/top_level.txt
iqa_calculator-2.0.0.dist-info/RECORD
