Metadata-Version: 2.4
Name: iqa_calculator
Version: 2.0.0
Summary: Pacote para calcular o Índice de Qualidade da Água (IQA)
Home-page: https://github.com/seitbnao/iqa_calculator
Author: Djunio Filho
Author-email: djuniormfilho@gmail.com
Classifier: Programming Language :: Python :: 3
Classifier: License :: OSI Approved :: MIT License
Classifier: Operating System :: OS Independent
Requires-Python: >=3.6
License-File: LICENSE
Dynamic: author
Dynamic: author-email
Dynamic: classifier
Dynamic: description
Dynamic: description-content-type
Dynamic: home-page
Dynamic: license-file
Dynamic: requires-python
Dynamic: summary
